eefunction/__init__.py
eefunction/property.py
eefunction-0.1.1.dist-info/LICENSE
eefunction-0.1.1.dist-info/METADATA
eefunction-0.1.1.dist-info/WHEEL
eefunction-0.1.1.dist-info/RECORD
